{"GlobalPropertiesHash":"1lXsihORCRJFNw61qzbRjgTOiqLQd6kG1lu2IlWU7qU=","FingerprintPatternsHash":"gq3WsqcKBUGTSNle7RKKyXRIwh7M8ccEqOqYvIzoM04=","PropertyOverridesHash":"8ZRc1sGeVrPBx4lD717BgRaQekyh78QKV9SKsdt638U=","InputHashes":["TFQAuydFDzYyujLM7wNZXGPPncUMDHcus9UUEISqaVQ=","i4wTF7Vwi3W1ERlfffb6R\u002BtbEmtxhfcumn1R7sWKiX8=","ba7\u002BF56NBGFdvaiG2eHTCEbkgQgaqGmqbG\u002BD5GBNtD8=","QghjGrdE2jwBxR\u002BTUhAmgKvkXIVK4dCoPkBXpeZckjo="],"CachedAssets":{"TFQAuydFDzYyujLM7wNZXGPPncUMDHcus9UUEISqaVQ=":{"Identity":"/Users/jay/Documents/Word Study/src/WordStudy.Api/wwwroot/app.js","SourceId":"WordStudy.Api","SourceType":"Discovered","ContentRoot":"/Users/jay/Documents/Word Study/src/WordStudy.Api/wwwroot/","BasePath":"/","RelativePath":"app#[.{fingerprint}]?.js","AssetKind":"All","AssetMode":"All","AssetRole":"Primary","AssetMergeBehavior":null,"AssetMergeSource":"","RelatedAsset":null,"AssetTraitName":null,"AssetTraitValue":null,"Fingerprint":"bsmbvb7q5f","Integrity":"G8P0DaBioAY4cts1LQUleGqjol5Fe4n2kqXawF/b1NU=","CopyToOutputDirectory":"Never","CopyToPublishDirectory":"PreserveNewest","OriginalItemSpec":"wwwroot/app.js","FileLength":15390,"LastWriteTime":"2026-06-02T02:51:15.7415727+00:00"},"i4wTF7Vwi3W1ERlfffb6R\u002BtbEmtxhfcumn1R7sWKiX8=":{"Identity":"/Users/jay/Documents/Word Study/src/WordStudy.Api/wwwroot/index.html","SourceId":"WordStudy.Api","SourceType":"Discovered","ContentRoot":"/Users/jay/Documents/Word Study/src/WordStudy.Api/wwwroot/","BasePath":"/","RelativePath":"index#[.{fingerprint}]?.html","AssetKind":"All","AssetMode":"All","AssetRole":"Primary","AssetMergeBehavior":null,"AssetMergeSource":"","RelatedAsset":null,"AssetTraitName":null,"AssetTraitValue":null,"Fingerprint":"n6g72adsr5","Integrity":"r8c0s0cJtg5LglLAzyJKaeflCxCCkcBE4XXwEsDswR8=","CopyToOutputDirectory":"Never","CopyToPublishDirectory":"PreserveNewest","OriginalItemSpec":"wwwroot/index.html","FileLength":492,"LastWriteTime":"2026-06-01T20:58:10.6742721+00:00"},"ba7\u002BF56NBGFdvaiG2eHTCEbkgQgaqGmqbG\u002BD5GBNtD8=":{"Identity":"/Users/jay/Documents/Word Study/src/WordStudy.Api/wwwroot/styles.css","SourceId":"WordStudy.Api","SourceType":"Discovered","ContentRoot":"/Users/jay/Documents/Word Study/src/WordStudy.Api/wwwroot/","BasePath":"/","RelativePath":"styles#[.{fingerprint}]?.css","AssetKind":"All","AssetMode":"All","AssetRole":"Primary","AssetMergeBehavior":null,"AssetMergeSource":"","RelatedAsset":null,"AssetTraitName":null,"AssetTraitValue":null,"Fingerprint":"9v5lxs95lb","Integrity":"9ZGGDo8atylQuVkOT13p9h5VLO383m1nv0lBZrbgDug=","CopyToOutputDirectory":"Never","CopyToPublishDirectory":"PreserveNewest","OriginalItemSpec":"wwwroot/styles.css","FileLength":5293,"LastWriteTime":"2026-06-02T02:34:39.4933366+00:00"}},"CachedCopyCandidates":{}}